pyfredapi/__about__.py
pyfredapi/__init__.py
pyfredapi/_base.py
pyfredapi/category.py
pyfredapi/maps.py
pyfredapi/py.typed
pyfredapi/releases.py
pyfredapi/series.py
pyfredapi/series_collection.py
pyfredapi/sources.py
pyfredapi/tags.py
pyfredapi/exceptions/__init__.py
pyfredapi/exceptions/exceptions.py
pyfredapi/utils/__init__.py
pyfredapi/utils/_common_type_hints.py
pyfredapi/utils/_convert_to_df.py
pyfredapi/utils/enums.py
pyfredapi-0.10.2.dist-info/METADATA
pyfredapi-0.10.2.dist-info/WHEEL
pyfredapi-0.10.2.dist-info/licenses/LICENSE
pyfredapi-0.10.2.dist-info/RECORD
