Metadata-Version: 2.4
Name: pyfredapi
Version: 0.10.2
Summary: A full featured API client for the FRED API web service.
Project-URL: Homepage, https://pyfredapi.readthedocs.io/en/latest/
Project-URL: Source, https://github.com/gw-moore/pyfredapi
Author-email: Greg Moore <gwmoore.career@gmail.com>
License-Expression: MIT
License-File: LICENSE
Keywords: economic data,economic data api,economic data api client,economic indicators,economic statistics,economic time series,economics,federal reserve,fred
Classifier: Development Status :: 4 - Beta
Classifier: Intended Audience :: Developers
Classifier: Intended Audience :: Financial and Insurance Industry
Classifier: Intended Audience :: Science/Research
Classifier: License :: OSI Approved :: MIT License
Classifier: Operating System :: OS Independent
Classifier: Programming Language :: Python :: 3.8
Classifier: Programming Language :: Python :: 3.9
Classifier: Programming Language :: Python :: 3.10
Classifier: Programming Language :: Python :: 3.11
Classifier: Programming Language :: Python :: 3.12
Requires-Python: >=3.8
Requires-Dist: pandas<3.0.0,>=1.0.0
Requires-Dist: pydantic<3.0.0,>=2.0.0
Requires-Dist: requests<3.0.0,>=2.0.0
Requires-Dist: rich<14.0.0,>=13.0.0
Provides-Extra: all
Requires-Dist: plotly<6.0.0,>=5.0.0; extra == 'all'
Requires-Dist: polars<2.0.0,>=1.0.0; extra == 'all'
Provides-Extra: dev
Requires-Dist: black[jupyter]==25.1.0; extra == 'dev'
Requires-Dist: coverage==7.4.4; extra == 'dev'
Requires-Dist: hatch==1.10.0; extra == 'dev'
Requires-Dist: jupyter==1.1.1; extra == 'dev'
Requires-Dist: mkdocs-jupyter==0.25.1; extra == 'dev'
Requires-Dist: mkdocs-material==9.5.50; extra == 'dev'
Requires-Dist: mkdocs==1.6.1; extra == 'dev'
Requires-Dist: mkdocstrings-python==1.13.0; extra == 'dev'
Requires-Dist: mypy==1.17.0; extra == 'dev'
Requires-Dist: pandas-stubs==2.3.0.250703; extra == 'dev'
Requires-Dist: pip-tools==7.4.1; extra == 'dev'
Requires-Dist: plotly<6.0.0,>=5.0.0; extra == 'dev'
Requires-Dist: plotly==5.18; extra == 'dev'
Requires-Dist: polars<2.0.0,>=1.0.0; extra == 'dev'
Requires-Dist: pre-commit==3.7.0; extra == 'dev'
Requires-Dist: pytest-cov==5.0.0; extra == 'dev'
Requires-Dist: pytest-recording==0.13.0; extra == 'dev'
Requires-Dist: pytest==8.1.1; extra == 'dev'
Requires-Dist: ruff==0.12.5; extra == 'dev'
Requires-Dist: seaborn==0.12.2; extra == 'dev'
Requires-Dist: tox==4.14.2; extra == 'dev'
Requires-Dist: types-requests==2.31.0.20240403; extra == 'dev'
Requires-Dist: types-setuptools==69.2.0.20240317; extra == 'dev'
Provides-Extra: docs
Requires-Dist: jupyter==1.1.1; extra == 'docs'
Requires-Dist: mkdocs-jupyter==0.25.1; extra == 'docs'
Requires-Dist: mkdocs-material==9.5.50; extra == 'docs'
Requires-Dist: mkdocs==1.6.1; extra == 'docs'
Requires-Dist: mkdocstrings-python==1.13.0; extra == 'docs'
Requires-Dist: plotly==5.18; extra == 'docs'
Requires-Dist: seaborn==0.12.2; extra == 'docs'
Provides-Extra: lint
Requires-Dist: black[jupyter]==25.1.0; extra == 'lint'
Requires-Dist: mypy==1.17.0; extra == 'lint'
Requires-Dist: pandas-stubs==2.3.0.250703; extra == 'lint'
Requires-Dist: pre-commit==3.7.0; extra == 'lint'
Requires-Dist: ruff==0.12.5; extra == 'lint'
Requires-Dist: types-requests==2.31.0.20240403; extra == 'lint'
Requires-Dist: types-setuptools==69.2.0.20240317; extra == 'lint'
Provides-Extra: plotly
Requires-Dist: plotly<6.0.0,>=5.0.0; extra == 'plotly'
Provides-Extra: polars
Requires-Dist: polars<2.0.0,>=1.0.0; extra == 'polars'
Provides-Extra: test
Requires-Dist: coverage==7.4.4; extra == 'test'
Requires-Dist: plotly<6.0.0,>=5.0.0; extra == 'test'
Requires-Dist: polars<2.0.0,>=1.0.0; extra == 'test'
Requires-Dist: pytest-cov==5.0.0; extra == 'test'
Requires-Dist: pytest-recording==0.13.0; extra == 'test'
Requires-Dist: pytest==8.1.1; extra == 'test'
Requires-Dist: tox==4.14.2; extra == 'test'
